Metadata-Version: 2.1
Name: gename
Version: 0.0.7
Summary: Guess gender from first name.
Home-page: http://github.com/sorl/gename
Author: Mikko Hellsing
Author-email: mikko@sumsum.se
License: ICS
Platform: UNKNOWN
Classifier: Development Status :: 5 - Production/Stable
Classifier: Intended Audience :: Developers
Classifier: License :: OSI Approved :: ISC License (ISCL)
Classifier: Operating System :: OS Independent
Classifier: Programming Language :: Python
Classifier: Programming Language :: Python :: 3.7
